nas/__init__.py
nas/composer/__init__.py
nas/composer/nn_composer.py
nas/composer/requirements.py
nas/data/__init__.py
nas/data/filters.py
nas/data/loader.py
nas/data/nas_data.py
nas/data/preprocessor.py
nas/data/time_series_preprocessing.py
nas/data/ts_dataset.py
nas/data/dataset/__init__.py
nas/data/dataset/builder.py
nas/data/dataset/torch_dataset.py
nas/graph/__init__.py
nas/graph/base_graph.py
nas/graph/graph_utils.py
nas/graph/nn_graph_verifier.py
nas/graph/builder/__init__.py
nas/graph/builder/base_graph_builder.py
nas/graph/builder/cnn_builder.py
nas/graph/node/__init__.py
nas/graph/node/nas_graph_node.py
nas/graph/node/nas_node_params.py
nas/graph/node/node_factory.py
nas/graph/node/params_counter.py
nas/model/__init__.py
nas/model/constructor.py
nas/model/model_interface.py
nas/model/pytorch/__init__.py
nas/model/pytorch/base_model.py
nas/model/pytorch/layers/__init__.py
nas/model/pytorch/layers/layer_initializer.py
nas/model/pytorch/layers/kan_convolutional/KANConv.py
nas/model/pytorch/layers/kan_convolutional/KANLinear.py
nas/model/pytorch/layers/kan_convolutional/__init__.py
nas/model/pytorch/layers/kan_convolutional/convolution.py
nas/model/pytorch/layers/torch_conv_kan/__init__.py
nas/model/pytorch/layers/torch_conv_kan/conv_kan.py
nas/model/pytorch/layers/torch_conv_kan/fast_kan_conv.py
nas/model/pytorch/layers/torch_conv_kan/layers.py
nas/model/pytorch/layers/torch_conv_kan/utils.py
nas/operations/__init__.py
nas/operations/validation_rules/__init__.py
nas/operations/validation_rules/cnn_val_rules.py
nas/optimizer/__init__.py
nas/optimizer/objective/__init__.py
nas/optimizer/objective/nas_cnn_optimiser.py
nas/optimizer/objective/nas_objective_evaluate.py
nas/optimizer/objective/objective.py
nas/repository/__init__.py
nas/repository/layer_types_enum.py
nas/utils/__init__.py
nas/utils/random_split_hack.py
nas/utils/utils.py
kan_o_nas-0.1.0.dist-info/METADATA
kan_o_nas-0.1.0.dist-info/WHEEL
kan_o_nas-0.1.0.dist-info/top_level.txt
kan_o_nas-0.1.0.dist-info/RECORD
