Metadata-Version: 2.4
Name: kan-o-nas
Version: 0.1.0
Summary: Evolutionary full NAS for fair comparison of CNN and KAN architectures (KAN'o'NAS).
Author: Vladimir Latypov, Alexander Hvatov
Project-URL: Homepage, https://github.com/ITMO-NSS-team/kan-o-nas
Project-URL: Issues, https://github.com/ITMO-NSS-team/kan-o-nas/issues
Keywords: NAS,evolutionary,KAN,CNN,neural-architecture-search
Classifier: Development Status :: 3 - Alpha
Classifier: Intended Audience :: Science/Research
Classifier: License :: OSI Approved :: MIT License
Classifier: Programming Language :: Python
Classifier: Programming Language :: Python :: 3
Classifier: Programming Language :: Python :: 3 :: Only
Classifier: Programming Language :: Python :: 3.9
Classifier: Programming Language :: Python :: 3.10
Classifier: Programming Language :: Python :: 3.11
Classifier: Programming Language :: Python :: 3.12
Classifier: Topic :: Scientific/Engineering :: Artificial Intelligence
Requires-Python: >=3.9
